aim3/__init__.py
aim3/aimcli.py
aim3/aimgui.py
aim3-18.10.29.3.data/scripts/aim
aim3-18.10.29.3.data/scripts/aimgui
aim3-18.10.29.3.dist-info/LICENSE
aim3-18.10.29.3.dist-info/METADATA
aim3-18.10.29.3.dist-info/WHEEL
aim3-18.10.29.3.dist-info/top_level.txt
aim3-18.10.29.3.dist-info/RECORD
