Metadata-Version: 2.1
Name: aim3
Version: 18.10.29.3
Summary: Simplistic tools for managing appimages with little effort.
Home-page: https://github.com/Kaiz0r/AppImages-Manager
Author: Kaiser
Author-email: kylebell68@gmail.com
License: UNKNOWN
Platform: UNKNOWN
Classifier: Programming Language :: Python :: 3
Classifier: License :: OSI Approved :: GNU General Public License (GPL)
Classifier: Operating System :: POSIX :: Linux
